ticket_universe/__init__.py
ticket_universe/charsets.py
ticket_universe/cli.py
ticket_universe/cli_test.py
ticket_universe/errors.py
ticket_universe/position.py
ticket_universe/position_test.py
ticket_universe/universe.py
ticket_universe/universe_test.py
ticket_universe-0.4.dist-info/LICENSE
ticket_universe-0.4.dist-info/METADATA
ticket_universe-0.4.dist-info/WHEEL
ticket_universe-0.4.dist-info/entry_points.txt
ticket_universe-0.4.dist-info/top_level.txt
ticket_universe-0.4.dist-info/RECORD
