Metadata-Version: 2.1
Name: ticket-universe
Version: 0.4
Summary: Toolset to generate ticket universes
Home-page: http://github.com/lotify/ticket_universe
Author: Eelke van den Bos
Author-email: eelke@moddix.com
License: MIT
Platform: UNKNOWN
